[{"heroId2":51,"matchCount":1919,"winCount":1024,"synergy":2.887,"__typename":"HeroStatsHeroDryadType"},{"heroId2":78,"matchCount":750,"winCount":398,"synergy":2.079,"__typename":"HeroStatsHeroDryadType"},{"heroId2":94,"matchCount":3808,"winCount":2038,"synergy":2.05,"__typename":"HeroStatsHeroDryadType"},{"heroId2":14,"matchCount":18123,"winCount":9372,"synergy":1.971,"__typename":"HeroStatsHeroDryadType"},{"heroId2":107,"matchCount":1252,"winCount":637,"synergy":1.934,"__typename":"HeroStatsHeroDryadType"},{"heroId2":113,"matchCount":4210,"winCount":2516,"synergy":1.902,"__typename":"HeroStatsHeroDryadType"},{"heroId2":77,"matchCount":848,"winCount":434,"synergy":1.886,"__typename":"HeroStatsHeroDryadType"},{"heroId2":92,"matchCount":1105,"winCount":588,"synergy":1.886,"__typename":"HeroStatsHeroDryadType"},{"heroId2":111,"matchCount":1539,"winCount":849,"synergy":1.521,"__typename":"HeroStatsHeroDryadType"},{"heroId2":20,"matchCount":5849,"winCount":3248,"synergy":1.518,"__typename":"HeroStatsHeroDryadType"},{"heroId2":60,"matchCount":3203,"winCount":1675,"synergy":1.512,"__typename":"HeroStatsHeroDryadType"},{"heroId2":55,"matchCount":1205,"winCount":669,"synergy":1.477,"__typename":"HeroStatsHeroDryadType"},{"heroId2":89,"matchCount":1403,"winCount":710,"synergy":1.431,"__typename":"HeroStatsHeroDryadType"},{"heroId2":13,"matchCount":5377,"winCount":2703,"synergy":1.395,"__typename":"HeroStatsHeroDryadType"},{"heroId2":33,"matchCount":1140,"winCount":579,"synergy":1.365,"__typename":"HeroStatsHeroDryadType"},{"heroId2":67,"matchCount":10813,"winCount":5623,"synergy":1.312,"__typename":"HeroStatsHeroDryadType"},{"heroId2":31,"matchCount":3695,"winCount":1964,"synergy":1.276,"__typename":"HeroStatsHeroDryadType"},{"heroId2":129,"matchCount":4679,"winCount":2260,"synergy":1.2,"__typename":"HeroStatsHeroDryadType"},{"heroId2":17,"matchCount":4795,"winCount":2393,"synergy":1.104,"__typename":"HeroStatsHeroDryadType"},{"heroId2":9,"matchCount":2626,"winCount":1287,"synergy":1.099,"__typename":"HeroStatsHeroDryadType"},{"heroId2":80,"matchCount":2325,"winCount":1255,"synergy":1.062,"__typename":"HeroStatsHeroDryadType"},{"heroId2":96,"matchCount":5364,"winCount":2813,"synergy":0.976,"__typename":"HeroStatsHeroDryadType"},{"heroId2":38,"matchCount":661,"winCount":308,"synergy":0.958,"__typename":"HeroStatsHeroDryadType"},{"heroId2":29,"matchCount":3192,"winCount":1605,"synergy":0.925,"__typename":"HeroStatsHeroDryadType"},{"heroId2":82,"matchCount":1987,"winCount":1166,"synergy":0.904,"__typename":"HeroStatsHeroDryadType"},{"heroId2":81,"matchCount":3833,"winCount":1848,"synergy":0.9,"__typename":"HeroStatsHeroDryadType"},{"heroId2":27,"matchCount":6432,"winCount":3451,"synergy":0.886,"__typename":"HeroStatsHeroDryadType"},{"heroId2":44,"matchCount":11436,"winCount":5292,"synergy":0.879,"__typename":"HeroStatsHeroDryadType"},{"heroId2":2,"matchCount":12498,"winCount":6679,"synergy":0.865,"__typename":"HeroStatsHeroDryadType"},{"heroId2":36,"matchCount":9489,"winCount":4961,"synergy":0.856,"__typename":"HeroStatsHeroDryadType"},{"heroId2":42,"matchCount":10969,"winCount":5946,"synergy":0.845,"__typename":"HeroStatsHeroDryadType"},{"heroId2":12,"matchCount":6744,"winCount":3516,"synergy":0.761,"__typename":"HeroStatsHeroDryadType"},{"heroId2":103,"matchCount":582,"winCount":302,"synergy":0.756,"__typename":"HeroStatsHeroDryadType"},{"heroId2":57,"matchCount":2981,"winCount":1431,"synergy":0.687,"__typename":"HeroStatsHeroDryadType"},{"heroId2":41,"matchCount":15326,"winCount":8034,"synergy":0.562,"__typename":"HeroStatsHeroDryadType"},{"heroId2":16,"matchCount":4437,"winCount":2446,"synergy":0.532,"__typename":"HeroStatsHeroDryadType"},{"heroId2":1,"matchCount":11359,"winCount":6014,"synergy":0.503,"__typename":"HeroStatsHeroDryadType"},{"heroId2":52,"matchCount":4885,"winCount":2614,"synergy":0.465,"__typename":"HeroStatsHeroDryadType"},{"heroId2":45,"matchCount":3466,"winCount":1732,"synergy":0.443,"__typename":"HeroStatsHeroDryadType"},{"heroId2":110,"matchCount":1902,"winCount":954,"synergy":0.442,"__typename":"HeroStatsHeroDryadType"},{"heroId2":137,"matchCount":3588,"winCount":1773,"synergy":0.435,"__typename":"HeroStatsHeroDryadType"},{"heroId2":100,"matchCount":3444,"winCount":1624,"synergy":0.429,"__typename":"HeroStatsHeroDryadType"},{"heroId2":88,"matchCount":4619,"winCount":2385,"synergy":0.425,"__typename":"HeroStatsHeroDryadType"},{"heroId2":54,"matchCount":7089,"winCount":3659,"synergy":0.391,"__typename":"HeroStatsHeroDryadType"},{"heroId2":102,"matchCount":9806,"winCount":5603,"synergy":0.363,"__typename":"HeroStatsHeroDryadType"},{"heroId2":22,"matchCount":9055,"winCount":4758,"synergy":0.358,"__typename":"HeroStatsHeroDryadType"},{"heroId2":59,"matchCount":4343,"winCount":2190,"synergy":0.357,"__typename":"HeroStatsHeroDryadType"},{"heroId2":104,"matchCount":12186,"winCount":6246,"synergy":0.352,"__typename":"HeroStatsHeroDryadType"},{"heroId2":76,"matchCount":9487,"winCount":5207,"synergy":0.303,"__typename":"HeroStatsHeroDryadType"},{"heroId2":8,"matchCount":10683,"winCount":5395,"synergy":0.245,"__typename":"HeroStatsHeroDryadType"},{"heroId2":71,"matchCount":13953,"winCount":6799,"synergy":0.215,"__typename":"HeroStatsHeroDryadType"},{"heroId2":49,"matchCount":3648,"winCount":1808,"synergy":0.212,"__typename":"HeroStatsHeroDryadType"},{"heroId2":106,"matchCount":3605,"winCount":1758,"synergy":0.206,"__typename":"HeroStatsHeroDryadType"},{"heroId2":11,"matchCount":7694,"winCount":3880,"synergy":0.201,"__typename":"HeroStatsHeroDryadType"},{"heroId2":39,"matchCount":5015,"winCount":2392,"synergy":0.196,"__typename":"HeroStatsHeroDryadType"},{"heroId2":126,"matchCount":2208,"winCount":1079,"synergy":0.187,"__typename":"HeroStatsHeroDryadType"},{"heroId2":56,"matchCount":5071,"winCount":2662,"synergy":0.164,"__typename":"HeroStatsHeroDryadType"},{"heroId2":95,"matchCount":3880,"winCount":2063,"synergy":0.158,"__typename":"HeroStatsHeroDryadType"},{"heroId2":48,"matchCount":6874,"winCount":3519,"synergy":0.138,"__typename":"HeroStatsHeroDryadType"},{"heroId2":84,"matchCount":7747,"winCount":4009,"synergy":0.106,"__typename":"HeroStatsHeroDryadType"},{"heroId2":7,"matchCount":7619,"winCount":3845,"synergy":0.096,"__typename":"HeroStatsHeroDryadType"},{"heroId2":26,"matchCount":10499,"winCount":5174,"synergy":0.088,"__typename":"HeroStatsHeroDryadType"},{"heroId2":19,"matchCount":3864,"winCount":1794,"synergy":0.017,"__typename":"HeroStatsHeroDryadType"},{"heroId2":40,"matchCount":4149,"winCount":2189,"synergy":-0.054,"__typename":"HeroStatsHeroDryadType"},{"heroId2":99,"matchCount":5518,"winCount":2780,"synergy":-0.07,"__typename":"HeroStatsHeroDryadType"},{"heroId2":61,"matchCount":1228,"winCount":571,"synergy":-0.13,"__typename":"HeroStatsHeroDryadType"},{"heroId2":73,"matchCount":2092,"winCount":1000,"synergy":-0.142,"__typename":"HeroStatsHeroDryadType"},{"heroId2":23,"matchCount":4466,"winCount":2242,"synergy":-0.17,"__typename":"HeroStatsHeroDryadType"},{"heroId2":93,"matchCount":11320,"winCount":5599,"synergy":-0.177,"__typename":"HeroStatsHeroDryadType"},{"heroId2":62,"matchCount":8254,"winCount":3976,"synergy":-0.268,"__typename":"HeroStatsHeroDryadType"},{"heroId2":25,"matchCount":8426,"winCount":3887,"synergy":-0.274,"__typename":"HeroStatsHeroDryadType"},{"heroId2":63,"matchCount":5837,"winCount":2810,"synergy":-0.304,"__typename":"HeroStatsHeroDryadType"},{"heroId2":34,"matchCount":2095,"winCount":1010,"synergy":-0.317,"__typename":"HeroStatsHeroDryadType"},{"heroId2":15,"matchCount":3233,"winCount":1564,"synergy":-0.317,"__typename":"HeroStatsHeroDryadType"},{"heroId2":123,"matchCount":3914,"winCount":1948,"synergy":-0.331,"__typename":"HeroStatsHeroDryadType"},{"heroId2":105,"matchCount":2664,"winCount":1317,"synergy":-0.345,"__typename":"HeroStatsHeroDryadType"},{"heroId2":4,"matchCount":2531,"winCount":1268,"synergy":-0.362,"__typename":"HeroStatsHeroDryadType"},{"heroId2":98,"matchCount":6349,"winCount":3285,"synergy":-0.363,"__typename":"HeroStatsHeroDryadType"},{"heroId2":119,"matchCount":2383,"winCount":1149,"synergy":-0.453,"__typename":"HeroStatsHeroDryadType"},{"heroId2":97,"matchCount":6323,"winCount":3054,"synergy":-0.461,"__typename":"HeroStatsHeroDryadType"},{"heroId2":69,"matchCount":2706,"winCount":1296,"synergy":-0.469,"__typename":"HeroStatsHeroDryadType"},{"heroId2":47,"matchCount":9119,"winCount":4850,"synergy":-0.472,"__typename":"HeroStatsHeroDryadType"},{"heroId2":43,"matchCount":5138,"winCount":2784,"synergy":-0.479,"__typename":"HeroStatsHeroDryadType"},{"heroId2":112,"matchCount":1594,"winCount":812,"synergy":-0.508,"__typename":"HeroStatsHeroDryadType"},{"heroId2":10,"matchCount":7701,"winCount":3534,"synergy":-0.654,"__typename":"HeroStatsHeroDryadType"},{"heroId2":101,"matchCount":4012,"winCount":1978,"synergy":-0.661,"__typename":"HeroStatsHeroDryadType"},{"heroId2":30,"matchCount":10066,"winCount":5458,"synergy":-0.706,"__typename":"HeroStatsHeroDryadType"},{"heroId2":5,"matchCount":4835,"winCount":2404,"synergy":-0.747,"__typename":"HeroStatsHeroDryadType"},{"heroId2":21,"matchCount":6383,"winCount":2903,"synergy":-0.812,"__typename":"HeroStatsHeroDryadType"},{"heroId2":86,"matchCount":6874,"winCount":3101,"synergy":-0.812,"__typename":"HeroStatsHeroDryadType"},{"heroId2":74,"matchCount":10255,"winCount":4975,"synergy":-0.871,"__typename":"HeroStatsHeroDryadType"},{"heroId2":70,"matchCount":5533,"winCount":2704,"synergy":-0.874,"__typename":"HeroStatsHeroDryadType"},{"heroId2":91,"matchCount":1300,"winCount":659,"synergy":-0.963,"__typename":"HeroStatsHeroDryadType"},{"heroId2":72,"matchCount":3885,"winCount":1849,"synergy":-0.972,"__typename":"HeroStatsHeroDryadType"},{"heroId2":37,"matchCount":3170,"winCount":1666,"synergy":-0.981,"__typename":"HeroStatsHeroDryadType"},{"heroId2":18,"matchCount":2773,"winCount":1296,"synergy":-1.131,"__typename":"HeroStatsHeroDryadType"},{"heroId2":138,"matchCount":3361,"winCount":1531,"synergy":-1.148,"__typename":"HeroStatsHeroDryadType"},{"heroId2":79,"matchCount":830,"winCount":388,"synergy":-1.226,"__typename":"HeroStatsHeroDryadType"},{"heroId2":114,"matchCount":4969,"winCount":2169,"synergy":-1.243,"__typename":"HeroStatsHeroDryadType"},{"heroId2":83,"matchCount":2405,"winCount":1227,"synergy":-1.244,"__typename":"HeroStatsHeroDryadType"},{"heroId2":28,"matchCount":12297,"winCount":6335,"synergy":-1.291,"__typename":"HeroStatsHeroDryadType"},{"heroId2":53,"matchCount":8686,"winCount":4138,"synergy":-1.305,"__typename":"HeroStatsHeroDryadType"},{"heroId2":6,"matchCount":10295,"winCount":5315,"synergy":-1.32,"__typename":"HeroStatsHeroDryadType"},{"heroId2":75,"matchCount":6035,"winCount":3033,"synergy":-1.341,"__typename":"HeroStatsHeroDryadType"},{"heroId2":35,"matchCount":14101,"winCount":6901,"synergy":-1.352,"__typename":"HeroStatsHeroDryadType"},{"heroId2":87,"matchCount":2351,"winCount":1141,"synergy":-1.384,"__typename":"HeroStatsHeroDryadType"},{"heroId2":32,"matchCount":4443,"winCount":2251,"synergy":-1.414,"__typename":"HeroStatsHeroDryadType"},{"heroId2":121,"matchCount":3619,"winCount":1757,"synergy":-1.481,"__typename":"HeroStatsHeroDryadType"},{"heroId2":3,"matchCount":994,"winCount":488,"synergy":-1.503,"__typename":"HeroStatsHeroDryadType"},{"heroId2":46,"matchCount":3825,"winCount":1705,"synergy":-1.512,"__typename":"HeroStatsHeroDryadType"},{"heroId2":109,"matchCount":1101,"winCount":488,"synergy":-1.542,"__typename":"HeroStatsHeroDryadType"},{"heroId2":108,"matchCount":2494,"winCount":1295,"synergy":-1.635,"__typename":"HeroStatsHeroDryadType"},{"heroId2":50,"matchCount":3764,"winCount":1804,"synergy":-1.658,"__typename":"HeroStatsHeroDryadType"},{"heroId2":65,"matchCount":991,"winCount":430,"synergy":-1.666,"__typename":"HeroStatsHeroDryadType"},{"heroId2":135,"matchCount":3231,"winCount":1563,"synergy":-1.786,"__typename":"HeroStatsHeroDryadType"},{"heroId2":136,"matchCount":1717,"winCount":818,"synergy":-1.941,"__typename":"HeroStatsHeroDryadType"},{"heroId2":64,"matchCount":6037,"winCount":3066,"synergy":-2.066,"__typename":"HeroStatsHeroDryadType"},{"heroId2":58,"matchCount":1248,"winCount":550,"synergy":-2.107,"__typename":"HeroStatsHeroDryadType"},{"heroId2":128,"matchCount":2592,"winCount":1131,"synergy":-2.308,"__typename":"HeroStatsHeroDryadType"},{"heroId2":85,"matchCount":3844,"winCount":1906,"synergy":-2.385,"__typename":"HeroStatsHeroDryadType"},{"heroId2":90,"matchCount":1002,"winCount":443,"synergy":-3.646,"__typename":"HeroStatsHeroDryadType"},{"heroId2":120,"matchCount":1647,"winCount":664,"synergy":-3.698,"__typename":"HeroStatsHeroDryadType"},{"heroId2":66,"matchCount":387,"winCount":161,"synergy":-6.581,"__typename":"HeroStatsHeroDryadType"}]