[{"heroId2":103,"matchCount":1225,"winCount":644,"synergy":3.964,"__typename":"HeroStatsHeroDryadType"},{"heroId2":99,"matchCount":9212,"winCount":4665,"synergy":2.672,"__typename":"HeroStatsHeroDryadType"},{"heroId2":34,"matchCount":6043,"winCount":2904,"synergy":2.127,"__typename":"HeroStatsHeroDryadType"},{"heroId2":135,"matchCount":5766,"winCount":2861,"synergy":1.959,"__typename":"HeroStatsHeroDryadType"},{"heroId2":113,"matchCount":10940,"winCount":6242,"synergy":1.751,"__typename":"HeroStatsHeroDryadType"},{"heroId2":61,"matchCount":3109,"winCount":1424,"synergy":1.728,"__typename":"HeroStatsHeroDryadType"},{"heroId2":52,"matchCount":10928,"winCount":5694,"synergy":1.595,"__typename":"HeroStatsHeroDryadType"},{"heroId2":11,"matchCount":20377,"winCount":10031,"synergy":1.558,"__typename":"HeroStatsHeroDryadType"},{"heroId2":108,"matchCount":3612,"winCount":1896,"synergy":1.496,"__typename":"HeroStatsHeroDryadType"},{"heroId2":98,"matchCount":10784,"winCount":5497,"synergy":1.471,"__typename":"HeroStatsHeroDryadType"},{"heroId2":43,"matchCount":10972,"winCount":5881,"synergy":1.464,"__typename":"HeroStatsHeroDryadType"},{"heroId2":36,"matchCount":21072,"winCount":10574,"synergy":1.297,"__typename":"HeroStatsHeroDryadType"},{"heroId2":29,"matchCount":5140,"winCount":2474,"synergy":1.269,"__typename":"HeroStatsHeroDryadType"},{"heroId2":64,"matchCount":21867,"winCount":11278,"synergy":1.263,"__typename":"HeroStatsHeroDryadType"},{"heroId2":73,"matchCount":4648,"winCount":2166,"synergy":1.18,"__typename":"HeroStatsHeroDryadType"},{"heroId2":48,"matchCount":17812,"winCount":8844,"synergy":1.177,"__typename":"HeroStatsHeroDryadType"},{"heroId2":7,"matchCount":15311,"winCount":7487,"synergy":1.036,"__typename":"HeroStatsHeroDryadType"},{"heroId2":54,"matchCount":18838,"winCount":9371,"synergy":1.022,"__typename":"HeroStatsHeroDryadType"},{"heroId2":138,"matchCount":9117,"winCount":4122,"synergy":1.011,"__typename":"HeroStatsHeroDryadType"},{"heroId2":94,"matchCount":9434,"winCount":4710,"synergy":0.991,"__typename":"HeroStatsHeroDryadType"},{"heroId2":110,"matchCount":5823,"winCount":2808,"synergy":0.975,"__typename":"HeroStatsHeroDryadType"},{"heroId2":30,"matchCount":36413,"winCount":19418,"synergy":0.943,"__typename":"HeroStatsHeroDryadType"},{"heroId2":92,"matchCount":2574,"winCount":1279,"synergy":0.928,"__typename":"HeroStatsHeroDryadType"},{"heroId2":45,"matchCount":11173,"winCount":5347,"synergy":0.892,"__typename":"HeroStatsHeroDryadType"},{"heroId2":35,"matchCount":38254,"winCount":18596,"synergy":0.892,"__typename":"HeroStatsHeroDryadType"},{"heroId2":37,"matchCount":11889,"winCount":6167,"synergy":0.881,"__typename":"HeroStatsHeroDryadType"},{"heroId2":22,"matchCount":24623,"winCount":12403,"synergy":0.806,"__typename":"HeroStatsHeroDryadType"},{"heroId2":8,"matchCount":25647,"winCount":12450,"synergy":0.792,"__typename":"HeroStatsHeroDryadType"},{"heroId2":63,"matchCount":15977,"winCount":7443,"synergy":0.743,"__typename":"HeroStatsHeroDryadType"},{"heroId2":55,"matchCount":2797,"winCount":1461,"synergy":0.716,"__typename":"HeroStatsHeroDryadType"},{"heroId2":90,"matchCount":3193,"winCount":1468,"synergy":0.713,"__typename":"HeroStatsHeroDryadType"},{"heroId2":112,"matchCount":5079,"winCount":2513,"synergy":0.633,"__typename":"HeroStatsHeroDryadType"},{"heroId2":6,"matchCount":27999,"winCount":14286,"synergy":0.621,"__typename":"HeroStatsHeroDryadType"},{"heroId2":59,"matchCount":9349,"winCount":4501,"synergy":0.593,"__typename":"HeroStatsHeroDryadType"},{"heroId2":23,"matchCount":8795,"winCount":4258,"synergy":0.567,"__typename":"HeroStatsHeroDryadType"},{"heroId2":95,"matchCount":9122,"winCount":4653,"synergy":0.506,"__typename":"HeroStatsHeroDryadType"},{"heroId2":76,"matchCount":22530,"winCount":11837,"synergy":0.432,"__typename":"HeroStatsHeroDryadType"},{"heroId2":58,"matchCount":3960,"winCount":1748,"synergy":0.421,"__typename":"HeroStatsHeroDryadType"},{"heroId2":33,"matchCount":3555,"winCount":1680,"synergy":0.397,"__typename":"HeroStatsHeroDryadType"},{"heroId2":16,"matchCount":7924,"winCount":4149,"synergy":0.37,"__typename":"HeroStatsHeroDryadType"},{"heroId2":47,"matchCount":20604,"winCount":10604,"synergy":0.363,"__typename":"HeroStatsHeroDryadType"},{"heroId2":15,"matchCount":7449,"winCount":3462,"synergy":0.338,"__typename":"HeroStatsHeroDryadType"},{"heroId2":129,"matchCount":7033,"winCount":3155,"synergy":0.338,"__typename":"HeroStatsHeroDryadType"},{"heroId2":70,"matchCount":13283,"winCount":6309,"synergy":0.253,"__typename":"HeroStatsHeroDryadType"},{"heroId2":18,"matchCount":6149,"winCount":2795,"synergy":0.224,"__typename":"HeroStatsHeroDryadType"},{"heroId2":75,"matchCount":19955,"winCount":9828,"synergy":0.201,"__typename":"HeroStatsHeroDryadType"},{"heroId2":10,"matchCount":17995,"winCount":7954,"synergy":0.187,"__typename":"HeroStatsHeroDryadType"},{"heroId2":25,"matchCount":23085,"winCount":10165,"synergy":0.167,"__typename":"HeroStatsHeroDryadType"},{"heroId2":81,"matchCount":6777,"winCount":3042,"synergy":0.133,"__typename":"HeroStatsHeroDryadType"},{"heroId2":96,"matchCount":7841,"winCount":3845,"synergy":0.116,"__typename":"HeroStatsHeroDryadType"},{"heroId2":123,"matchCount":11202,"winCount":5338,"synergy":0.106,"__typename":"HeroStatsHeroDryadType"},{"heroId2":2,"matchCount":19221,"winCount":9633,"synergy":0.098,"__typename":"HeroStatsHeroDryadType"},{"heroId2":80,"matchCount":5206,"winCount":2630,"synergy":0.098,"__typename":"HeroStatsHeroDryadType"},{"heroId2":28,"matchCount":19935,"winCount":10025,"synergy":0.051,"__typename":"HeroStatsHeroDryadType"},{"heroId2":46,"matchCount":10000,"winCount":4365,"synergy":0.029,"__typename":"HeroStatsHeroDryadType"},{"heroId2":68,"matchCount":14044,"winCount":6807,"synergy":0.013,"__typename":"HeroStatsHeroDryadType"},{"heroId2":136,"matchCount":4255,"winCount":1999,"synergy":-0.004,"__typename":"HeroStatsHeroDryadType"},{"heroId2":97,"matchCount":12051,"winCount":5562,"synergy":-0.022,"__typename":"HeroStatsHeroDryadType"},{"heroId2":106,"matchCount":8476,"winCount":3896,"synergy":-0.043,"__typename":"HeroStatsHeroDryadType"},{"heroId2":39,"matchCount":12747,"winCount":5723,"synergy":-0.056,"__typename":"HeroStatsHeroDryadType"},{"heroId2":13,"matchCount":12706,"winCount":5888,"synergy":-0.059,"__typename":"HeroStatsHeroDryadType"},{"heroId2":102,"matchCount":18662,"winCount":10101,"synergy":-0.095,"__typename":"HeroStatsHeroDryadType"},{"heroId2":114,"matchCount":11704,"winCount":4946,"synergy":-0.099,"__typename":"HeroStatsHeroDryadType"},{"heroId2":137,"matchCount":6000,"winCount":2778,"synergy":-0.121,"__typename":"HeroStatsHeroDryadType"},{"heroId2":31,"matchCount":14881,"winCount":7327,"synergy":-0.166,"__typename":"HeroStatsHeroDryadType"},{"heroId2":38,"matchCount":1068,"winCount":458,"synergy":-0.181,"__typename":"HeroStatsHeroDryadType"},{"heroId2":119,"matchCount":7642,"winCount":3511,"synergy":-0.208,"__typename":"HeroStatsHeroDryadType"},{"heroId2":50,"matchCount":14079,"winCount":6592,"synergy":-0.22,"__typename":"HeroStatsHeroDryadType"},{"heroId2":121,"matchCount":17453,"winCount":8215,"synergy":-0.348,"__typename":"HeroStatsHeroDryadType"},{"heroId2":1,"matchCount":28976,"winCount":14335,"synergy":-0.351,"__typename":"HeroStatsHeroDryadType"},{"heroId2":84,"matchCount":20296,"winCount":9890,"synergy":-0.353,"__typename":"HeroStatsHeroDryadType"},{"heroId2":128,"matchCount":7382,"winCount":3174,"synergy":-0.361,"__typename":"HeroStatsHeroDryadType"},{"heroId2":44,"matchCount":28308,"winCount":12037,"synergy":-0.376,"__typename":"HeroStatsHeroDryadType"},{"heroId2":56,"matchCount":13254,"winCount":6541,"synergy":-0.399,"__typename":"HeroStatsHeroDryadType"},{"heroId2":101,"matchCount":12524,"winCount":5882,"synergy":-0.422,"__typename":"HeroStatsHeroDryadType"},{"heroId2":93,"matchCount":26569,"winCount":12398,"synergy":-0.433,"__typename":"HeroStatsHeroDryadType"},{"heroId2":49,"matchCount":6322,"winCount":2933,"synergy":-0.44,"__typename":"HeroStatsHeroDryadType"},{"heroId2":120,"matchCount":3799,"winCount":1558,"synergy":-0.456,"__typename":"HeroStatsHeroDryadType"},{"heroId2":32,"matchCount":10966,"winCount":5389,"synergy":-0.464,"__typename":"HeroStatsHeroDryadType"},{"heroId2":86,"matchCount":22654,"winCount":9713,"synergy":-0.466,"__typename":"HeroStatsHeroDryadType"},{"heroId2":12,"matchCount":15206,"winCount":7351,"synergy":-0.494,"__typename":"HeroStatsHeroDryadType"},{"heroId2":42,"matchCount":19502,"winCount":9809,"synergy":-0.508,"__typename":"HeroStatsHeroDryadType"},{"heroId2":65,"matchCount":2433,"winCount":1022,"synergy":-0.514,"__typename":"HeroStatsHeroDryadType"},{"heroId2":60,"matchCount":5357,"winCount":2553,"synergy":-0.531,"__typename":"HeroStatsHeroDryadType"},{"heroId2":9,"matchCount":7806,"winCount":3497,"synergy":-0.56,"__typename":"HeroStatsHeroDryadType"},{"heroId2":74,"matchCount":25983,"winCount":12001,"synergy":-0.636,"__typename":"HeroStatsHeroDryadType"},{"heroId2":69,"matchCount":4626,"winCount":2091,"synergy":-0.65,"__typename":"HeroStatsHeroDryadType"},{"heroId2":107,"matchCount":2936,"winCount":1343,"synergy":-0.702,"__typename":"HeroStatsHeroDryadType"},{"heroId2":4,"matchCount":5978,"winCount":2824,"synergy":-0.705,"__typename":"HeroStatsHeroDryadType"},{"heroId2":40,"matchCount":12844,"winCount":6367,"synergy":-0.714,"__typename":"HeroStatsHeroDryadType"},{"heroId2":67,"matchCount":26985,"winCount":12800,"synergy":-0.739,"__typename":"HeroStatsHeroDryadType"},{"heroId2":87,"matchCount":9482,"winCount":4418,"synergy":-0.746,"__typename":"HeroStatsHeroDryadType"},{"heroId2":5,"matchCount":19712,"winCount":9285,"synergy":-0.801,"__typename":"HeroStatsHeroDryadType"},{"heroId2":85,"matchCount":10137,"winCount":4927,"synergy":-0.84,"__typename":"HeroStatsHeroDryadType"},{"heroId2":53,"matchCount":27806,"winCount":12655,"synergy":-0.865,"__typename":"HeroStatsHeroDryadType"},{"heroId2":21,"matchCount":16671,"winCount":7157,"synergy":-0.868,"__typename":"HeroStatsHeroDryadType"},{"heroId2":77,"matchCount":1596,"winCount":732,"synergy":-0.874,"__typename":"HeroStatsHeroDryadType"},{"heroId2":57,"matchCount":6026,"winCount":2645,"synergy":-0.876,"__typename":"HeroStatsHeroDryadType"},{"heroId2":41,"matchCount":30044,"winCount":14544,"synergy":-0.902,"__typename":"HeroStatsHeroDryadType"},{"heroId2":72,"matchCount":10990,"winCount":4960,"synergy":-0.931,"__typename":"HeroStatsHeroDryadType"},{"heroId2":19,"matchCount":7668,"winCount":3291,"synergy":-0.956,"__typename":"HeroStatsHeroDryadType"},{"heroId2":17,"matchCount":11975,"winCount":5430,"synergy":-0.96,"__typename":"HeroStatsHeroDryadType"},{"heroId2":111,"matchCount":6778,"winCount":3395,"synergy":-1.032,"__typename":"HeroStatsHeroDryadType"},{"heroId2":126,"matchCount":5329,"winCount":2405,"synergy":-1.08,"__typename":"HeroStatsHeroDryadType"},{"heroId2":105,"matchCount":8334,"winCount":3839,"synergy":-1.09,"__typename":"HeroStatsHeroDryadType"},{"heroId2":109,"matchCount":2816,"winCount":1187,"synergy":-1.094,"__typename":"HeroStatsHeroDryadType"},{"heroId2":104,"matchCount":21878,"winCount":10357,"synergy":-1.107,"__typename":"HeroStatsHeroDryadType"},{"heroId2":91,"matchCount":5143,"winCount":2469,"synergy":-1.131,"__typename":"HeroStatsHeroDryadType"},{"heroId2":88,"matchCount":11655,"winCount":5536,"synergy":-1.141,"__typename":"HeroStatsHeroDryadType"},{"heroId2":26,"matchCount":37433,"winCount":17006,"synergy":-1.268,"__typename":"HeroStatsHeroDryadType"},{"heroId2":62,"matchCount":20922,"winCount":9333,"synergy":-1.329,"__typename":"HeroStatsHeroDryadType"},{"heroId2":20,"matchCount":18718,"winCount":9356,"synergy":-1.443,"__typename":"HeroStatsHeroDryadType"},{"heroId2":27,"matchCount":23186,"winCount":11313,"synergy":-1.474,"__typename":"HeroStatsHeroDryadType"},{"heroId2":79,"matchCount":3010,"winCount":1321,"synergy":-1.492,"__typename":"HeroStatsHeroDryadType"},{"heroId2":78,"matchCount":1201,"winCount":563,"synergy":-1.572,"__typename":"HeroStatsHeroDryadType"},{"heroId2":100,"matchCount":7244,"winCount":3087,"synergy":-1.61,"__typename":"HeroStatsHeroDryadType"},{"heroId2":66,"matchCount":1576,"winCount":693,"synergy":-1.635,"__typename":"HeroStatsHeroDryadType"},{"heroId2":82,"matchCount":4972,"winCount":2664,"synergy":-1.669,"__typename":"HeroStatsHeroDryadType"},{"heroId2":83,"matchCount":8159,"winCount":3904,"synergy":-1.901,"__typename":"HeroStatsHeroDryadType"},{"heroId2":89,"matchCount":3311,"winCount":1479,"synergy":-1.962,"__typename":"HeroStatsHeroDryadType"},{"heroId2":14,"matchCount":39436,"winCount":17828,"synergy":-1.983,"__typename":"HeroStatsHeroDryadType"},{"heroId2":51,"matchCount":3749,"winCount":1715,"synergy":-2.275,"__typename":"HeroStatsHeroDryadType"},{"heroId2":3,"matchCount":3535,"winCount":1595,"synergy":-2.927,"__typename":"HeroStatsHeroDryadType"}]