[{"heroId2":78,"matchCount":571,"winCount":324,"synergy":4.113,"__typename":"HeroStatsHeroDryadType"},{"heroId2":55,"matchCount":1015,"winCount":532,"synergy":3.772,"__typename":"HeroStatsHeroDryadType"},{"heroId2":38,"matchCount":495,"winCount":295,"synergy":3.086,"__typename":"HeroStatsHeroDryadType"},{"heroId2":79,"matchCount":1292,"winCount":728,"synergy":2.88,"__typename":"HeroStatsHeroDryadType"},{"heroId2":63,"matchCount":5985,"winCount":3363,"synergy":2.479,"__typename":"HeroStatsHeroDryadType"},{"heroId2":54,"matchCount":5380,"winCount":2874,"synergy":2.457,"__typename":"HeroStatsHeroDryadType"},{"heroId2":21,"matchCount":6001,"winCount":3522,"synergy":2.36,"__typename":"HeroStatsHeroDryadType"},{"heroId2":108,"matchCount":2013,"winCount":1016,"synergy":2.344,"__typename":"HeroStatsHeroDryadType"},{"heroId2":6,"matchCount":9483,"winCount":4895,"synergy":2.288,"__typename":"HeroStatsHeroDryadType"},{"heroId2":90,"matchCount":1308,"winCount":736,"synergy":2.183,"__typename":"HeroStatsHeroDryadType"},{"heroId2":65,"matchCount":1283,"winCount":748,"synergy":2.179,"__typename":"HeroStatsHeroDryadType"},{"heroId2":98,"matchCount":5588,"winCount":2839,"synergy":2.134,"__typename":"HeroStatsHeroDryadType"},{"heroId2":96,"matchCount":4050,"winCount":2155,"synergy":2.119,"__typename":"HeroStatsHeroDryadType"},{"heroId2":51,"matchCount":1938,"winCount":1043,"synergy":2.082,"__typename":"HeroStatsHeroDryadType"},{"heroId2":22,"matchCount":8831,"winCount":4644,"synergy":2.054,"__typename":"HeroStatsHeroDryadType"},{"heroId2":39,"matchCount":4530,"winCount":2557,"synergy":2.028,"__typename":"HeroStatsHeroDryadType"},{"heroId2":97,"matchCount":5637,"winCount":3133,"synergy":1.876,"__typename":"HeroStatsHeroDryadType"},{"heroId2":137,"matchCount":3043,"winCount":1669,"synergy":1.765,"__typename":"HeroStatsHeroDryadType"},{"heroId2":16,"matchCount":3869,"winCount":1918,"synergy":1.685,"__typename":"HeroStatsHeroDryadType"},{"heroId2":83,"matchCount":3651,"winCount":1892,"synergy":1.645,"__typename":"HeroStatsHeroDryadType"},{"heroId2":57,"matchCount":2918,"winCount":1657,"synergy":1.619,"__typename":"HeroStatsHeroDryadType"},{"heroId2":111,"matchCount":2524,"winCount":1273,"synergy":1.615,"__typename":"HeroStatsHeroDryadType"},{"heroId2":100,"matchCount":3625,"winCount":2071,"synergy":1.607,"__typename":"HeroStatsHeroDryadType"},{"heroId2":30,"matchCount":15001,"winCount":7291,"synergy":1.607,"__typename":"HeroStatsHeroDryadType"},{"heroId2":45,"matchCount":4538,"winCount":2467,"synergy":1.596,"__typename":"HeroStatsHeroDryadType"},{"heroId2":128,"matchCount":2957,"winCount":1704,"synergy":1.576,"__typename":"HeroStatsHeroDryadType"},{"heroId2":15,"matchCount":3148,"winCount":1721,"synergy":1.498,"__typename":"HeroStatsHeroDryadType"},{"heroId2":109,"matchCount":858,"winCount":499,"synergy":1.468,"__typename":"HeroStatsHeroDryadType"},{"heroId2":74,"matchCount":8742,"winCount":4764,"synergy":1.338,"__typename":"HeroStatsHeroDryadType"},{"heroId2":49,"matchCount":2579,"winCount":1408,"synergy":1.334,"__typename":"HeroStatsHeroDryadType"},{"heroId2":37,"matchCount":4854,"winCount":2432,"synergy":1.324,"__typename":"HeroStatsHeroDryadType"},{"heroId2":31,"matchCount":5900,"winCount":3039,"synergy":1.315,"__typename":"HeroStatsHeroDryadType"},{"heroId2":92,"matchCount":1163,"winCount":618,"synergy":1.221,"__typename":"HeroStatsHeroDryadType"},{"heroId2":19,"matchCount":3170,"winCount":1824,"synergy":1.182,"__typename":"HeroStatsHeroDryadType"},{"heroId2":91,"matchCount":2184,"winCount":1134,"synergy":1.111,"__typename":"HeroStatsHeroDryadType"},{"heroId2":8,"matchCount":8847,"winCount":4782,"synergy":1.095,"__typename":"HeroStatsHeroDryadType"},{"heroId2":120,"matchCount":1377,"winCount":825,"synergy":1.064,"__typename":"HeroStatsHeroDryadType"},{"heroId2":129,"matchCount":3719,"winCount":2119,"synergy":1.04,"__typename":"HeroStatsHeroDryadType"},{"heroId2":123,"matchCount":4827,"winCount":2548,"synergy":0.967,"__typename":"HeroStatsHeroDryadType"},{"heroId2":105,"matchCount":3438,"winCount":1839,"synergy":0.954,"__typename":"HeroStatsHeroDryadType"},{"heroId2":35,"matchCount":13000,"winCount":6875,"synergy":0.787,"__typename":"HeroStatsHeroDryadType"},{"heroId2":64,"matchCount":8554,"winCount":4315,"synergy":0.745,"__typename":"HeroStatsHeroDryadType"},{"heroId2":71,"matchCount":13962,"winCount":7620,"synergy":0.682,"__typename":"HeroStatsHeroDryadType"},{"heroId2":12,"matchCount":5633,"winCount":2901,"synergy":0.614,"__typename":"HeroStatsHeroDryadType"},{"heroId2":138,"matchCount":3479,"winCount":1968,"synergy":0.572,"__typename":"HeroStatsHeroDryadType"},{"heroId2":5,"matchCount":7618,"winCount":3952,"synergy":0.547,"__typename":"HeroStatsHeroDryadType"},{"heroId2":72,"matchCount":4855,"winCount":2614,"synergy":0.525,"__typename":"HeroStatsHeroDryadType"},{"heroId2":50,"matchCount":5238,"winCount":2806,"synergy":0.503,"__typename":"HeroStatsHeroDryadType"},{"heroId2":46,"matchCount":2992,"winCount":1697,"synergy":0.462,"__typename":"HeroStatsHeroDryadType"},{"heroId2":25,"matchCount":8234,"winCount":4676,"synergy":0.462,"__typename":"HeroStatsHeroDryadType"},{"heroId2":17,"matchCount":4471,"winCount":2426,"synergy":0.459,"__typename":"HeroStatsHeroDryadType"},{"heroId2":88,"matchCount":5211,"winCount":2699,"synergy":0.418,"__typename":"HeroStatsHeroDryadType"},{"heroId2":70,"matchCount":4765,"winCount":2526,"synergy":0.364,"__typename":"HeroStatsHeroDryadType"},{"heroId2":23,"matchCount":3596,"winCount":1891,"synergy":0.335,"__typename":"HeroStatsHeroDryadType"},{"heroId2":85,"matchCount":4632,"winCount":2345,"synergy":0.329,"__typename":"HeroStatsHeroDryadType"},{"heroId2":136,"matchCount":1968,"winCount":1053,"synergy":0.315,"__typename":"HeroStatsHeroDryadType"},{"heroId2":135,"matchCount":2656,"winCount":1396,"synergy":0.314,"__typename":"HeroStatsHeroDryadType"},{"heroId2":107,"matchCount":1408,"winCount":763,"synergy":0.186,"__typename":"HeroStatsHeroDryadType"},{"heroId2":40,"matchCount":5609,"winCount":2772,"synergy":0.136,"__typename":"HeroStatsHeroDryadType"},{"heroId2":36,"matchCount":7713,"winCount":3959,"synergy":0.13,"__typename":"HeroStatsHeroDryadType"},{"heroId2":68,"matchCount":5336,"winCount":2748,"synergy":0.128,"__typename":"HeroStatsHeroDryadType"},{"heroId2":101,"matchCount":4913,"winCount":2569,"synergy":0.088,"__typename":"HeroStatsHeroDryadType"},{"heroId2":110,"matchCount":2337,"winCount":1230,"synergy":0.085,"__typename":"HeroStatsHeroDryadType"},{"heroId2":126,"matchCount":1837,"winCount":997,"synergy":-0.133,"__typename":"HeroStatsHeroDryadType"},{"heroId2":13,"matchCount":4877,"winCount":2590,"synergy":-0.155,"__typename":"HeroStatsHeroDryadType"},{"heroId2":20,"matchCount":7746,"winCount":3731,"synergy":-0.207,"__typename":"HeroStatsHeroDryadType"},{"heroId2":42,"matchCount":9453,"winCount":4621,"synergy":-0.261,"__typename":"HeroStatsHeroDryadType"},{"heroId2":106,"matchCount":2992,"winCount":1656,"synergy":-0.269,"__typename":"HeroStatsHeroDryadType"},{"heroId2":67,"matchCount":9627,"winCount":4949,"synergy":-0.318,"__typename":"HeroStatsHeroDryadType"},{"heroId2":76,"matchCount":9277,"winCount":4157,"synergy":-0.318,"__typename":"HeroStatsHeroDryadType"},{"heroId2":48,"matchCount":6006,"winCount":3071,"synergy":-0.364,"__typename":"HeroStatsHeroDryadType"},{"heroId2":7,"matchCount":7115,"winCount":3669,"synergy":-0.37,"__typename":"HeroStatsHeroDryadType"},{"heroId2":121,"matchCount":5746,"winCount":2960,"synergy":-0.437,"__typename":"HeroStatsHeroDryadType"},{"heroId2":52,"matchCount":6874,"winCount":3183,"synergy":-0.471,"__typename":"HeroStatsHeroDryadType"},{"heroId2":43,"matchCount":4551,"winCount":2102,"synergy":-0.472,"__typename":"HeroStatsHeroDryadType"},{"heroId2":86,"matchCount":8893,"winCount":4975,"synergy":-0.512,"__typename":"HeroStatsHeroDryadType"},{"heroId2":18,"matchCount":2089,"winCount":1139,"synergy":-0.552,"__typename":"HeroStatsHeroDryadType"},{"heroId2":62,"matchCount":8928,"winCount":4743,"synergy":-0.581,"__typename":"HeroStatsHeroDryadType"},{"heroId2":26,"matchCount":15198,"winCount":7982,"synergy":-0.604,"__typename":"HeroStatsHeroDryadType"},{"heroId2":9,"matchCount":3440,"winCount":1852,"synergy":-0.634,"__typename":"HeroStatsHeroDryadType"},{"heroId2":119,"matchCount":3126,"winCount":1668,"synergy":-0.65,"__typename":"HeroStatsHeroDryadType"},{"heroId2":112,"matchCount":2020,"winCount":1023,"synergy":-0.66,"__typename":"HeroStatsHeroDryadType"},{"heroId2":14,"matchCount":17111,"winCount":8877,"synergy":-0.691,"__typename":"HeroStatsHeroDryadType"},{"heroId2":94,"matchCount":3932,"winCount":1965,"synergy":-0.698,"__typename":"HeroStatsHeroDryadType"},{"heroId2":53,"matchCount":10816,"winCount":5656,"synergy":-0.786,"__typename":"HeroStatsHeroDryadType"},{"heroId2":104,"matchCount":9818,"winCount":4987,"synergy":-0.811,"__typename":"HeroStatsHeroDryadType"},{"heroId2":114,"matchCount":4162,"winCount":2370,"synergy":-0.82,"__typename":"HeroStatsHeroDryadType"},{"heroId2":1,"matchCount":11490,"winCount":5594,"synergy":-0.821,"__typename":"HeroStatsHeroDryadType"},{"heroId2":44,"matchCount":10173,"winCount":5755,"synergy":-0.885,"__typename":"HeroStatsHeroDryadType"},{"heroId2":87,"matchCount":3625,"winCount":1861,"synergy":-1.017,"__typename":"HeroStatsHeroDryadType"},{"heroId2":47,"matchCount":8434,"winCount":3940,"synergy":-1.087,"__typename":"HeroStatsHeroDryadType"},{"heroId2":10,"matchCount":6594,"winCount":3620,"synergy":-1.19,"__typename":"HeroStatsHeroDryadType"},{"heroId2":69,"matchCount":2488,"winCount":1290,"synergy":-1.218,"__typename":"HeroStatsHeroDryadType"},{"heroId2":77,"matchCount":739,"winCount":384,"synergy":-1.334,"__typename":"HeroStatsHeroDryadType"},{"heroId2":3,"matchCount":1369,"winCount":687,"synergy":-1.414,"__typename":"HeroStatsHeroDryadType"},{"heroId2":61,"matchCount":1168,"winCount":642,"synergy":-1.422,"__typename":"HeroStatsHeroDryadType"},{"heroId2":93,"matchCount":10074,"winCount":5133,"synergy":-1.428,"__typename":"HeroStatsHeroDryadType"},{"heroId2":84,"matchCount":8683,"winCount":4244,"synergy":-1.429,"__typename":"HeroStatsHeroDryadType"},{"heroId2":11,"matchCount":6442,"winCount":3262,"synergy":-1.443,"__typename":"HeroStatsHeroDryadType"},{"heroId2":33,"matchCount":1467,"winCount":750,"synergy":-1.447,"__typename":"HeroStatsHeroDryadType"},{"heroId2":56,"matchCount":4940,"winCount":2398,"synergy":-1.479,"__typename":"HeroStatsHeroDryadType"},{"heroId2":2,"matchCount":9332,"winCount":4525,"synergy":-1.513,"__typename":"HeroStatsHeroDryadType"},{"heroId2":4,"matchCount":1991,"winCount":996,"synergy":-1.514,"__typename":"HeroStatsHeroDryadType"},{"heroId2":75,"matchCount":7228,"winCount":3545,"synergy":-1.548,"__typename":"HeroStatsHeroDryadType"},{"heroId2":102,"matchCount":9639,"winCount":4186,"synergy":-1.645,"__typename":"HeroStatsHeroDryadType"},{"heroId2":95,"matchCount":3078,"winCount":1455,"synergy":-1.657,"__typename":"HeroStatsHeroDryadType"},{"heroId2":34,"matchCount":1881,"winCount":987,"synergy":-1.682,"__typename":"HeroStatsHeroDryadType"},{"heroId2":99,"matchCount":3833,"winCount":1943,"synergy":-1.723,"__typename":"HeroStatsHeroDryadType"},{"heroId2":27,"matchCount":8574,"winCount":4099,"synergy":-1.81,"__typename":"HeroStatsHeroDryadType"},{"heroId2":59,"matchCount":3415,"winCount":1731,"synergy":-1.832,"__typename":"HeroStatsHeroDryadType"},{"heroId2":28,"matchCount":10319,"winCount":4905,"synergy":-1.969,"__typename":"HeroStatsHeroDryadType"},{"heroId2":103,"matchCount":593,"winCount":291,"synergy":-2.073,"__typename":"HeroStatsHeroDryadType"},{"heroId2":113,"matchCount":3430,"winCount":1440,"synergy":-2.113,"__typename":"HeroStatsHeroDryadType"},{"heroId2":89,"matchCount":1260,"winCount":644,"synergy":-2.246,"__typename":"HeroStatsHeroDryadType"},{"heroId2":60,"matchCount":2504,"winCount":1235,"synergy":-2.257,"__typename":"HeroStatsHeroDryadType"},{"heroId2":29,"matchCount":2454,"winCount":1249,"synergy":-2.409,"__typename":"HeroStatsHeroDryadType"},{"heroId2":66,"matchCount":693,"winCount":355,"synergy":-2.862,"__typename":"HeroStatsHeroDryadType"},{"heroId2":58,"matchCount":1618,"winCount":853,"synergy":-3.04,"__typename":"HeroStatsHeroDryadType"},{"heroId2":32,"matchCount":3971,"winCount":1876,"synergy":-3.147,"__typename":"HeroStatsHeroDryadType"},{"heroId2":81,"matchCount":3073,"winCount":1597,"synergy":-3.286,"__typename":"HeroStatsHeroDryadType"},{"heroId2":80,"matchCount":2040,"winCount":937,"synergy":-3.352,"__typename":"HeroStatsHeroDryadType"},{"heroId2":82,"matchCount":1529,"winCount":614,"synergy":-4.178,"__typename":"HeroStatsHeroDryadType"},{"heroId2":73,"matchCount":1688,"winCount":835,"synergy":-4.341,"__typename":"HeroStatsHeroDryadType"}]