[{"heroId2":137,"matchCount":572,"winCount":332,"synergy":6.711,"__typename":"HeroStatsHeroDryadType"},{"heroId2":107,"matchCount":244,"winCount":143,"synergy":6.267,"__typename":"HeroStatsHeroDryadType"},{"heroId2":78,"matchCount":137,"winCount":78,"synergy":6.253,"__typename":"HeroStatsHeroDryadType"},{"heroId2":60,"matchCount":479,"winCount":260,"synergy":4.496,"__typename":"HeroStatsHeroDryadType"},{"heroId2":66,"matchCount":101,"winCount":57,"synergy":4.063,"__typename":"HeroStatsHeroDryadType"},{"heroId2":93,"matchCount":1496,"winCount":808,"synergy":3.278,"__typename":"HeroStatsHeroDryadType"},{"heroId2":71,"matchCount":2589,"winCount":1432,"synergy":3.08,"__typename":"HeroStatsHeroDryadType"},{"heroId2":38,"matchCount":90,"winCount":52,"synergy":3.009,"__typename":"HeroStatsHeroDryadType"},{"heroId2":138,"matchCount":593,"winCount":340,"synergy":2.988,"__typename":"HeroStatsHeroDryadType"},{"heroId2":83,"matchCount":665,"winCount":342,"synergy":2.904,"__typename":"HeroStatsHeroDryadType"},{"heroId2":77,"matchCount":121,"winCount":66,"synergy":2.901,"__typename":"HeroStatsHeroDryadType"},{"heroId2":7,"matchCount":1425,"winCount":756,"synergy":2.835,"__typename":"HeroStatsHeroDryadType"},{"heroId2":113,"matchCount":529,"winCount":238,"synergy":2.62,"__typename":"HeroStatsHeroDryadType"},{"heroId2":88,"matchCount":1070,"winCount":559,"synergy":2.585,"__typename":"HeroStatsHeroDryadType"},{"heroId2":6,"matchCount":1374,"winCount":690,"synergy":2.578,"__typename":"HeroStatsHeroDryadType"},{"heroId2":35,"matchCount":2367,"winCount":1253,"synergy":2.509,"__typename":"HeroStatsHeroDryadType"},{"heroId2":52,"matchCount":1118,"winCount":532,"synergy":2.477,"__typename":"HeroStatsHeroDryadType"},{"heroId2":18,"matchCount":396,"winCount":220,"synergy":2.267,"__typename":"HeroStatsHeroDryadType"},{"heroId2":36,"matchCount":1478,"winCount":763,"synergy":2.172,"__typename":"HeroStatsHeroDryadType"},{"heroId2":104,"matchCount":1618,"winCount":842,"synergy":2.054,"__typename":"HeroStatsHeroDryadType"},{"heroId2":74,"matchCount":1617,"winCount":863,"synergy":1.977,"__typename":"HeroStatsHeroDryadType"},{"heroId2":62,"matchCount":1587,"winCount":856,"synergy":1.956,"__typename":"HeroStatsHeroDryadType"},{"heroId2":96,"matchCount":868,"winCount":444,"synergy":1.892,"__typename":"HeroStatsHeroDryadType"},{"heroId2":5,"matchCount":1358,"winCount":699,"synergy":1.853,"__typename":"HeroStatsHeroDryadType"},{"heroId2":105,"matchCount":558,"winCount":293,"synergy":1.707,"__typename":"HeroStatsHeroDryadType"},{"heroId2":106,"matchCount":604,"winCount":334,"synergy":1.653,"__typename":"HeroStatsHeroDryadType"},{"heroId2":136,"matchCount":341,"winCount":181,"synergy":1.642,"__typename":"HeroStatsHeroDryadType"},{"heroId2":20,"matchCount":1505,"winCount":724,"synergy":1.374,"__typename":"HeroStatsHeroDryadType"},{"heroId2":135,"matchCount":534,"winCount":277,"synergy":1.351,"__typename":"HeroStatsHeroDryadType"},{"heroId2":16,"matchCount":745,"winCount":354,"synergy":1.326,"__typename":"HeroStatsHeroDryadType"},{"heroId2":94,"matchCount":642,"winCount":323,"synergy":1.306,"__typename":"HeroStatsHeroDryadType"},{"heroId2":11,"matchCount":1140,"winCount":587,"synergy":1.14,"__typename":"HeroStatsHeroDryadType"},{"heroId2":108,"matchCount":400,"winCount":190,"synergy":1.098,"__typename":"HeroStatsHeroDryadType"},{"heroId2":39,"matchCount":864,"winCount":464,"synergy":1.002,"__typename":"HeroStatsHeroDryadType"},{"heroId2":9,"matchCount":617,"winCount":331,"synergy":0.956,"__typename":"HeroStatsHeroDryadType"},{"heroId2":37,"matchCount":886,"winCount":425,"synergy":0.95,"__typename":"HeroStatsHeroDryadType"},{"heroId2":72,"matchCount":906,"winCount":476,"synergy":0.929,"__typename":"HeroStatsHeroDryadType"},{"heroId2":23,"matchCount":665,"winCount":342,"synergy":0.89,"__typename":"HeroStatsHeroDryadType"},{"heroId2":95,"matchCount":464,"winCount":223,"synergy":0.871,"__typename":"HeroStatsHeroDryadType"},{"heroId2":101,"matchCount":908,"winCount":467,"synergy":0.846,"__typename":"HeroStatsHeroDryadType"},{"heroId2":112,"matchCount":308,"winCount":155,"synergy":0.761,"__typename":"HeroStatsHeroDryadType"},{"heroId2":34,"matchCount":346,"winCount":184,"synergy":0.732,"__typename":"HeroStatsHeroDryadType"},{"heroId2":31,"matchCount":1077,"winCount":530,"synergy":0.72,"__typename":"HeroStatsHeroDryadType"},{"heroId2":2,"matchCount":1676,"winCount":821,"synergy":0.716,"__typename":"HeroStatsHeroDryadType"},{"heroId2":109,"matchCount":174,"winCount":97,"synergy":0.614,"__typename":"HeroStatsHeroDryadType"},{"heroId2":25,"matchCount":1513,"winCount":835,"synergy":0.59,"__typename":"HeroStatsHeroDryadType"},{"heroId2":99,"matchCount":672,"winCount":345,"synergy":0.582,"__typename":"HeroStatsHeroDryadType"},{"heroId2":84,"matchCount":1490,"winCount":733,"synergy":0.547,"__typename":"HeroStatsHeroDryadType"},{"heroId2":27,"matchCount":1722,"winCount":832,"synergy":0.409,"__typename":"HeroStatsHeroDryadType"},{"heroId2":42,"matchCount":1490,"winCount":712,"synergy":0.377,"__typename":"HeroStatsHeroDryadType"},{"heroId2":100,"matchCount":728,"winCount":394,"synergy":0.327,"__typename":"HeroStatsHeroDryadType"},{"heroId2":33,"matchCount":252,"winCount":129,"synergy":0.308,"__typename":"HeroStatsHeroDryadType"},{"heroId2":123,"matchCount":828,"winCount":417,"synergy":0.267,"__typename":"HeroStatsHeroDryadType"},{"heroId2":21,"matchCount":1168,"winCount":641,"synergy":0.198,"__typename":"HeroStatsHeroDryadType"},{"heroId2":46,"matchCount":592,"winCount":324,"synergy":0.19,"__typename":"HeroStatsHeroDryadType"},{"heroId2":67,"matchCount":1513,"winCount":760,"synergy":0.185,"__typename":"HeroStatsHeroDryadType"},{"heroId2":45,"matchCount":839,"winCount":430,"synergy":0.167,"__typename":"HeroStatsHeroDryadType"},{"heroId2":29,"matchCount":471,"winCount":244,"synergy":0.15,"__typename":"HeroStatsHeroDryadType"},{"heroId2":64,"matchCount":1620,"winCount":779,"synergy":0.145,"__typename":"HeroStatsHeroDryadType"},{"heroId2":68,"matchCount":982,"winCount":488,"synergy":0.059,"__typename":"HeroStatsHeroDryadType"},{"heroId2":54,"matchCount":1125,"winCount":553,"synergy":0.028,"__typename":"HeroStatsHeroDryadType"},{"heroId2":56,"matchCount":830,"winCount":401,"synergy":0.018,"__typename":"HeroStatsHeroDryadType"},{"heroId2":129,"matchCount":734,"winCount":398,"synergy":0.011,"__typename":"HeroStatsHeroDryadType"},{"heroId2":3,"matchCount":261,"winCount":130,"synergy":-0.125,"__typename":"HeroStatsHeroDryadType"},{"heroId2":8,"matchCount":1571,"winCount":803,"synergy":-0.156,"__typename":"HeroStatsHeroDryadType"},{"heroId2":120,"matchCount":288,"winCount":164,"synergy":-0.193,"__typename":"HeroStatsHeroDryadType"},{"heroId2":10,"matchCount":1074,"winCount":582,"synergy":-0.201,"__typename":"HeroStatsHeroDryadType"},{"heroId2":63,"matchCount":929,"winCount":480,"synergy":-0.262,"__typename":"HeroStatsHeroDryadType"},{"heroId2":26,"matchCount":2961,"winCount":1514,"synergy":-0.28,"__typename":"HeroStatsHeroDryadType"},{"heroId2":14,"matchCount":3311,"winCount":1675,"synergy":-0.282,"__typename":"HeroStatsHeroDryadType"},{"heroId2":44,"matchCount":1570,"winCount":869,"synergy":-0.39,"__typename":"HeroStatsHeroDryadType"},{"heroId2":119,"matchCount":545,"winCount":283,"synergy":-0.398,"__typename":"HeroStatsHeroDryadType"},{"heroId2":58,"matchCount":296,"winCount":158,"synergy":-0.664,"__typename":"HeroStatsHeroDryadType"},{"heroId2":22,"matchCount":1617,"winCount":777,"synergy":-0.718,"__typename":"HeroStatsHeroDryadType"},{"heroId2":87,"matchCount":659,"winCount":329,"synergy":-0.755,"__typename":"HeroStatsHeroDryadType"},{"heroId2":40,"matchCount":993,"winCount":464,"synergy":-0.812,"__typename":"HeroStatsHeroDryadType"},{"heroId2":111,"matchCount":448,"winCount":207,"synergy":-0.841,"__typename":"HeroStatsHeroDryadType"},{"heroId2":89,"matchCount":180,"winCount":91,"synergy":-0.883,"__typename":"HeroStatsHeroDryadType"},{"heroId2":110,"matchCount":480,"winCount":239,"synergy":-0.922,"__typename":"HeroStatsHeroDryadType"},{"heroId2":121,"matchCount":1061,"winCount":523,"synergy":-0.932,"__typename":"HeroStatsHeroDryadType"},{"heroId2":102,"matchCount":1663,"winCount":703,"synergy":-1.063,"__typename":"HeroStatsHeroDryadType"},{"heroId2":28,"matchCount":1805,"winCount":843,"synergy":-1.067,"__typename":"HeroStatsHeroDryadType"},{"heroId2":19,"matchCount":565,"winCount":302,"synergy":-1.08,"__typename":"HeroStatsHeroDryadType"},{"heroId2":91,"matchCount":323,"winCount":155,"synergy":-1.121,"__typename":"HeroStatsHeroDryadType"},{"heroId2":86,"matchCount":1672,"winCount":895,"synergy":-1.205,"__typename":"HeroStatsHeroDryadType"},{"heroId2":30,"matchCount":2721,"winCount":1198,"synergy":-1.275,"__typename":"HeroStatsHeroDryadType"},{"heroId2":85,"matchCount":786,"winCount":371,"synergy":-1.354,"__typename":"HeroStatsHeroDryadType"},{"heroId2":12,"matchCount":953,"winCount":456,"synergy":-1.408,"__typename":"HeroStatsHeroDryadType"},{"heroId2":81,"matchCount":476,"winCount":248,"synergy":-1.438,"__typename":"HeroStatsHeroDryadType"},{"heroId2":128,"matchCount":558,"winCount":295,"synergy":-1.459,"__typename":"HeroStatsHeroDryadType"},{"heroId2":4,"matchCount":356,"winCount":172,"synergy":-1.515,"__typename":"HeroStatsHeroDryadType"},{"heroId2":97,"matchCount":1111,"winCount":561,"synergy":-1.516,"__typename":"HeroStatsHeroDryadType"},{"heroId2":75,"matchCount":1371,"winCount":649,"synergy":-1.527,"__typename":"HeroStatsHeroDryadType"},{"heroId2":48,"matchCount":1074,"winCount":517,"synergy":-1.628,"__typename":"HeroStatsHeroDryadType"},{"heroId2":17,"matchCount":738,"winCount":373,"synergy":-1.638,"__typename":"HeroStatsHeroDryadType"},{"heroId2":50,"matchCount":883,"winCount":439,"synergy":-1.658,"__typename":"HeroStatsHeroDryadType"},{"heroId2":13,"matchCount":925,"winCount":461,"synergy":-1.751,"__typename":"HeroStatsHeroDryadType"},{"heroId2":114,"matchCount":792,"winCount":429,"synergy":-1.82,"__typename":"HeroStatsHeroDryadType"},{"heroId2":126,"matchCount":375,"winCount":190,"synergy":-2.018,"__typename":"HeroStatsHeroDryadType"},{"heroId2":41,"matchCount":1979,"winCount":917,"synergy":-2.049,"__typename":"HeroStatsHeroDryadType"},{"heroId2":47,"matchCount":1505,"winCount":662,"synergy":-2.11,"__typename":"HeroStatsHeroDryadType"},{"heroId2":70,"matchCount":858,"winCount":418,"synergy":-2.197,"__typename":"HeroStatsHeroDryadType"},{"heroId2":59,"matchCount":614,"winCount":298,"synergy":-2.347,"__typename":"HeroStatsHeroDryadType"},{"heroId2":57,"matchCount":542,"winCount":277,"synergy":-2.431,"__typename":"HeroStatsHeroDryadType"},{"heroId2":53,"matchCount":1959,"winCount":954,"synergy":-2.681,"__typename":"HeroStatsHeroDryadType"},{"heroId2":80,"matchCount":391,"winCount":175,"synergy":-2.723,"__typename":"HeroStatsHeroDryadType"},{"heroId2":1,"matchCount":1595,"winCount":720,"synergy":-2.727,"__typename":"HeroStatsHeroDryadType"},{"heroId2":69,"matchCount":440,"winCount":213,"synergy":-2.904,"__typename":"HeroStatsHeroDryadType"},{"heroId2":73,"matchCount":303,"winCount":149,"synergy":-2.962,"__typename":"HeroStatsHeroDryadType"},{"heroId2":65,"matchCount":240,"winCount":123,"synergy":-3.216,"__typename":"HeroStatsHeroDryadType"},{"heroId2":98,"matchCount":1083,"winCount":471,"synergy":-3.546,"__typename":"HeroStatsHeroDryadType"},{"heroId2":79,"matchCount":255,"winCount":123,"synergy":-3.571,"__typename":"HeroStatsHeroDryadType"},{"heroId2":15,"matchCount":505,"winCount":242,"synergy":-3.625,"__typename":"HeroStatsHeroDryadType"},{"heroId2":82,"matchCount":293,"winCount":113,"synergy":-4.016,"__typename":"HeroStatsHeroDryadType"},{"heroId2":55,"matchCount":189,"winCount":81,"synergy":-4.079,"__typename":"HeroStatsHeroDryadType"},{"heroId2":76,"matchCount":1594,"winCount":628,"synergy":-4.102,"__typename":"HeroStatsHeroDryadType"},{"heroId2":103,"matchCount":117,"winCount":53,"synergy":-4.119,"__typename":"HeroStatsHeroDryadType"},{"heroId2":32,"matchCount":678,"winCount":302,"synergy":-4.136,"__typename":"HeroStatsHeroDryadType"},{"heroId2":49,"matchCount":474,"winCount":224,"synergy":-4.221,"__typename":"HeroStatsHeroDryadType"},{"heroId2":43,"matchCount":809,"winCount":329,"synergy":-4.345,"__typename":"HeroStatsHeroDryadType"},{"heroId2":90,"matchCount":277,"winCount":133,"synergy":-4.441,"__typename":"HeroStatsHeroDryadType"},{"heroId2":61,"matchCount":193,"winCount":93,"synergy":-6.524,"__typename":"HeroStatsHeroDryadType"},{"heroId2":92,"matchCount":195,"winCount":79,"synergy":-9.552,"__typename":"HeroStatsHeroDryadType"}]