[{"heroId2":55,"matchCount":161,"winCount":94,"synergy":8.944,"__typename":"HeroStatsHeroDryadType"},{"heroId2":1,"matchCount":1693,"winCount":973,"synergy":7.196,"__typename":"HeroStatsHeroDryadType"},{"heroId2":3,"matchCount":292,"winCount":170,"synergy":5.798,"__typename":"HeroStatsHeroDryadType"},{"heroId2":101,"matchCount":980,"winCount":570,"synergy":5.169,"__typename":"HeroStatsHeroDryadType"},{"heroId2":113,"matchCount":710,"winCount":355,"synergy":5.143,"__typename":"HeroStatsHeroDryadType"},{"heroId2":92,"matchCount":243,"winCount":140,"synergy":5.072,"__typename":"HeroStatsHeroDryadType"},{"heroId2":60,"matchCount":514,"winCount":293,"synergy":4.719,"__typename":"HeroStatsHeroDryadType"},{"heroId2":91,"matchCount":407,"winCount":229,"synergy":4.702,"__typename":"HeroStatsHeroDryadType"},{"heroId2":39,"matchCount":813,"winCount":482,"synergy":4.126,"__typename":"HeroStatsHeroDryadType"},{"heroId2":66,"matchCount":146,"winCount":86,"synergy":4.086,"__typename":"HeroStatsHeroDryadType"},{"heroId2":82,"matchCount":335,"winCount":164,"synergy":3.907,"__typename":"HeroStatsHeroDryadType"},{"heroId2":45,"matchCount":865,"winCount":497,"synergy":3.89,"__typename":"HeroStatsHeroDryadType"},{"heroId2":42,"matchCount":1539,"winCount":823,"synergy":3.6,"__typename":"HeroStatsHeroDryadType"},{"heroId2":33,"matchCount":250,"winCount":141,"synergy":3.032,"__typename":"HeroStatsHeroDryadType"},{"heroId2":41,"matchCount":2065,"winCount":1111,"synergy":2.974,"__typename":"HeroStatsHeroDryadType"},{"heroId2":67,"matchCount":1587,"winCount":879,"synergy":2.908,"__typename":"HeroStatsHeroDryadType"},{"heroId2":129,"matchCount":726,"winCount":432,"synergy":2.834,"__typename":"HeroStatsHeroDryadType"},{"heroId2":22,"matchCount":1627,"winCount":881,"synergy":2.805,"__typename":"HeroStatsHeroDryadType"},{"heroId2":102,"matchCount":1883,"winCount":915,"synergy":2.76,"__typename":"HeroStatsHeroDryadType"},{"heroId2":69,"matchCount":432,"winCount":244,"synergy":2.719,"__typename":"HeroStatsHeroDryadType"},{"heroId2":14,"matchCount":3614,"winCount":2024,"synergy":2.641,"__typename":"HeroStatsHeroDryadType"},{"heroId2":137,"matchCount":613,"winCount":345,"synergy":2.534,"__typename":"HeroStatsHeroDryadType"},{"heroId2":17,"matchCount":765,"winCount":437,"synergy":2.485,"__typename":"HeroStatsHeroDryadType"},{"heroId2":10,"matchCount":1084,"winCount":643,"synergy":2.422,"__typename":"HeroStatsHeroDryadType"},{"heroId2":51,"matchCount":394,"winCount":216,"synergy":2.323,"__typename":"HeroStatsHeroDryadType"},{"heroId2":32,"matchCount":702,"winCount":375,"synergy":2.287,"__typename":"HeroStatsHeroDryadType"},{"heroId2":27,"matchCount":1720,"winCount":904,"synergy":2.232,"__typename":"HeroStatsHeroDryadType"},{"heroId2":38,"matchCount":101,"winCount":60,"synergy":2.132,"__typename":"HeroStatsHeroDryadType"},{"heroId2":96,"matchCount":737,"winCount":397,"synergy":2.115,"__typename":"HeroStatsHeroDryadType"},{"heroId2":18,"matchCount":385,"winCount":223,"synergy":2.09,"__typename":"HeroStatsHeroDryadType"},{"heroId2":49,"matchCount":446,"winCount":249,"synergy":1.802,"__typename":"HeroStatsHeroDryadType"},{"heroId2":65,"matchCount":273,"winCount":160,"synergy":1.707,"__typename":"HeroStatsHeroDryadType"},{"heroId2":13,"matchCount":937,"winCount":522,"synergy":1.672,"__typename":"HeroStatsHeroDryadType"},{"heroId2":88,"matchCount":941,"winCount":505,"synergy":1.608,"__typename":"HeroStatsHeroDryadType"},{"heroId2":43,"matchCount":888,"winCount":436,"synergy":1.578,"__typename":"HeroStatsHeroDryadType"},{"heroId2":84,"matchCount":1534,"winCount":808,"synergy":1.57,"__typename":"HeroStatsHeroDryadType"},{"heroId2":119,"matchCount":568,"winCount":320,"synergy":1.525,"__typename":"HeroStatsHeroDryadType"},{"heroId2":8,"matchCount":1477,"winCount":814,"synergy":1.367,"__typename":"HeroStatsHeroDryadType"},{"heroId2":104,"matchCount":1820,"winCount":977,"synergy":1.277,"__typename":"HeroStatsHeroDryadType"},{"heroId2":73,"matchCount":331,"winCount":185,"synergy":1.261,"__typename":"HeroStatsHeroDryadType"},{"heroId2":74,"matchCount":1847,"winCount":1018,"synergy":1.2,"__typename":"HeroStatsHeroDryadType"},{"heroId2":70,"matchCount":879,"winCount":478,"synergy":1.026,"__typename":"HeroStatsHeroDryadType"},{"heroId2":97,"matchCount":1047,"winCount":581,"synergy":1.007,"__typename":"HeroStatsHeroDryadType"},{"heroId2":121,"matchCount":1084,"winCount":582,"synergy":0.992,"__typename":"HeroStatsHeroDryadType"},{"heroId2":68,"matchCount":977,"winCount":519,"synergy":0.982,"__typename":"HeroStatsHeroDryadType"},{"heroId2":23,"matchCount":651,"winCount":351,"synergy":0.913,"__typename":"HeroStatsHeroDryadType"},{"heroId2":111,"matchCount":564,"winCount":284,"synergy":0.882,"__typename":"HeroStatsHeroDryadType"},{"heroId2":30,"matchCount":2618,"winCount":1271,"synergy":0.748,"__typename":"HeroStatsHeroDryadType"},{"heroId2":61,"matchCount":251,"winCount":145,"synergy":0.599,"__typename":"HeroStatsHeroDryadType"},{"heroId2":71,"matchCount":2533,"winCount":1398,"synergy":0.503,"__typename":"HeroStatsHeroDryadType"},{"heroId2":93,"matchCount":1634,"winCount":877,"synergy":0.502,"__typename":"HeroStatsHeroDryadType"},{"heroId2":4,"matchCount":406,"winCount":214,"synergy":0.408,"__typename":"HeroStatsHeroDryadType"},{"heroId2":86,"matchCount":1723,"winCount":991,"synergy":0.318,"__typename":"HeroStatsHeroDryadType"},{"heroId2":25,"matchCount":1588,"winCount":912,"synergy":0.313,"__typename":"HeroStatsHeroDryadType"},{"heroId2":12,"matchCount":963,"winCount":500,"synergy":0.215,"__typename":"HeroStatsHeroDryadType"},{"heroId2":28,"matchCount":1896,"winCount":955,"synergy":0.156,"__typename":"HeroStatsHeroDryadType"},{"heroId2":98,"matchCount":1126,"winCount":558,"synergy":0.077,"__typename":"HeroStatsHeroDryadType"},{"heroId2":100,"matchCount":684,"winCount":385,"synergy":0.05,"__typename":"HeroStatsHeroDryadType"},{"heroId2":135,"matchCount":496,"winCount":263,"synergy":-0.026,"__typename":"HeroStatsHeroDryadType"},{"heroId2":46,"matchCount":655,"winCount":373,"synergy":-0.087,"__typename":"HeroStatsHeroDryadType"},{"heroId2":72,"matchCount":874,"winCount":470,"synergy":-0.248,"__typename":"HeroStatsHeroDryadType"},{"heroId2":94,"matchCount":649,"winCount":332,"synergy":-0.271,"__typename":"HeroStatsHeroDryadType"},{"heroId2":36,"matchCount":1470,"winCount":758,"synergy":-0.305,"__typename":"HeroStatsHeroDryadType"},{"heroId2":26,"matchCount":3024,"winCount":1619,"synergy":-0.357,"__typename":"HeroStatsHeroDryadType"},{"heroId2":89,"matchCount":209,"winCount":112,"synergy":-0.36,"__typename":"HeroStatsHeroDryadType"},{"heroId2":75,"matchCount":1444,"winCount":735,"synergy":-0.404,"__typename":"HeroStatsHeroDryadType"},{"heroId2":78,"matchCount":129,"winCount":68,"synergy":-0.424,"__typename":"HeroStatsHeroDryadType"},{"heroId2":2,"matchCount":1763,"winCount":886,"synergy":-0.461,"__typename":"HeroStatsHeroDryadType"},{"heroId2":56,"matchCount":894,"winCount":449,"synergy":-0.558,"__typename":"HeroStatsHeroDryadType"},{"heroId2":76,"matchCount":1916,"winCount":869,"synergy":-0.578,"__typename":"HeroStatsHeroDryadType"},{"heroId2":11,"matchCount":1302,"winCount":678,"synergy":-0.737,"__typename":"HeroStatsHeroDryadType"},{"heroId2":40,"matchCount":1022,"winCount":503,"synergy":-0.789,"__typename":"HeroStatsHeroDryadType"},{"heroId2":62,"matchCount":1641,"winCount":880,"synergy":-0.821,"__typename":"HeroStatsHeroDryadType"},{"heroId2":5,"matchCount":1484,"winCount":762,"synergy":-0.824,"__typename":"HeroStatsHeroDryadType"},{"heroId2":106,"matchCount":521,"winCount":288,"synergy":-0.824,"__typename":"HeroStatsHeroDryadType"},{"heroId2":114,"matchCount":759,"winCount":437,"synergy":-0.897,"__typename":"HeroStatsHeroDryadType"},{"heroId2":19,"matchCount":622,"winCount":349,"synergy":-0.957,"__typename":"HeroStatsHeroDryadType"},{"heroId2":47,"matchCount":1588,"winCount":755,"synergy":-1.087,"__typename":"HeroStatsHeroDryadType"},{"heroId2":126,"matchCount":340,"winCount":184,"synergy":-1.095,"__typename":"HeroStatsHeroDryadType"},{"heroId2":128,"matchCount":551,"winCount":307,"synergy":-1.136,"__typename":"HeroStatsHeroDryadType"},{"heroId2":77,"matchCount":155,"winCount":82,"synergy":-1.176,"__typename":"HeroStatsHeroDryadType"},{"heroId2":9,"matchCount":633,"winCount":341,"synergy":-1.221,"__typename":"HeroStatsHeroDryadType"},{"heroId2":20,"matchCount":1606,"winCount":770,"synergy":-1.303,"__typename":"HeroStatsHeroDryadType"},{"heroId2":34,"matchCount":374,"winCount":200,"synergy":-1.445,"__typename":"HeroStatsHeroDryadType"},{"heroId2":107,"matchCount":276,"winCount":147,"synergy":-1.51,"__typename":"HeroStatsHeroDryadType"},{"heroId2":35,"matchCount":2383,"winCount":1221,"synergy":-1.668,"__typename":"HeroStatsHeroDryadType"},{"heroId2":53,"matchCount":2066,"winCount":1076,"synergy":-1.758,"__typename":"HeroStatsHeroDryadType"},{"heroId2":99,"matchCount":712,"winCount":366,"synergy":-1.795,"__typename":"HeroStatsHeroDryadType"},{"heroId2":48,"matchCount":1147,"winCount":578,"synergy":-1.804,"__typename":"HeroStatsHeroDryadType"},{"heroId2":63,"matchCount":1057,"winCount":556,"synergy":-1.839,"__typename":"HeroStatsHeroDryadType"},{"heroId2":50,"matchCount":1020,"winCount":528,"synergy":-2.035,"__typename":"HeroStatsHeroDryadType"},{"heroId2":79,"matchCount":251,"winCount":131,"synergy":-2.048,"__typename":"HeroStatsHeroDryadType"},{"heroId2":138,"matchCount":585,"winCount":320,"synergy":-2.089,"__typename":"HeroStatsHeroDryadType"},{"heroId2":57,"matchCount":558,"winCount":301,"synergy":-2.107,"__typename":"HeroStatsHeroDryadType"},{"heroId2":83,"matchCount":697,"winCount":340,"synergy":-2.173,"__typename":"HeroStatsHeroDryadType"},{"heroId2":90,"matchCount":296,"winCount":156,"synergy":-2.217,"__typename":"HeroStatsHeroDryadType"},{"heroId2":105,"matchCount":636,"winCount":324,"synergy":-2.37,"__typename":"HeroStatsHeroDryadType"},{"heroId2":95,"matchCount":615,"winCount":291,"synergy":-2.406,"__typename":"HeroStatsHeroDryadType"},{"heroId2":136,"matchCount":381,"winCount":195,"synergy":-2.735,"__typename":"HeroStatsHeroDryadType"},{"heroId2":29,"matchCount":451,"winCount":231,"synergy":-2.927,"__typename":"HeroStatsHeroDryadType"},{"heroId2":110,"matchCount":460,"winCount":231,"synergy":-2.999,"__typename":"HeroStatsHeroDryadType"},{"heroId2":6,"matchCount":1642,"winCount":774,"synergy":-2.999,"__typename":"HeroStatsHeroDryadType"},{"heroId2":123,"matchCount":923,"winCount":458,"synergy":-3.01,"__typename":"HeroStatsHeroDryadType"},{"heroId2":87,"matchCount":706,"winCount":354,"synergy":-3.032,"__typename":"HeroStatsHeroDryadType"},{"heroId2":64,"matchCount":1579,"winCount":745,"synergy":-3.232,"__typename":"HeroStatsHeroDryadType"},{"heroId2":31,"matchCount":1099,"winCount":524,"synergy":-3.257,"__typename":"HeroStatsHeroDryadType"},{"heroId2":21,"matchCount":1180,"winCount":635,"synergy":-3.379,"__typename":"HeroStatsHeroDryadType"},{"heroId2":85,"matchCount":870,"winCount":414,"synergy":-3.431,"__typename":"HeroStatsHeroDryadType"},{"heroId2":7,"matchCount":1389,"winCount":685,"synergy":-3.442,"__typename":"HeroStatsHeroDryadType"},{"heroId2":44,"matchCount":1609,"winCount":875,"synergy":-3.867,"__typename":"HeroStatsHeroDryadType"},{"heroId2":112,"matchCount":423,"winCount":203,"synergy":-4.016,"__typename":"HeroStatsHeroDryadType"},{"heroId2":59,"matchCount":720,"winCount":352,"synergy":-4.424,"__typename":"HeroStatsHeroDryadType"},{"heroId2":37,"matchCount":898,"winCount":405,"synergy":-4.427,"__typename":"HeroStatsHeroDryadType"},{"heroId2":108,"matchCount":350,"winCount":155,"synergy":-4.579,"__typename":"HeroStatsHeroDryadType"},{"heroId2":16,"matchCount":718,"winCount":315,"synergy":-4.751,"__typename":"HeroStatsHeroDryadType"},{"heroId2":54,"matchCount":1160,"winCount":542,"synergy":-4.948,"__typename":"HeroStatsHeroDryadType"},{"heroId2":120,"matchCount":324,"winCount":177,"synergy":-4.969,"__typename":"HeroStatsHeroDryadType"},{"heroId2":15,"matchCount":574,"winCount":281,"synergy":-5.002,"__typename":"HeroStatsHeroDryadType"},{"heroId2":58,"matchCount":295,"winCount":152,"synergy":-5.041,"__typename":"HeroStatsHeroDryadType"},{"heroId2":103,"matchCount":111,"winCount":52,"synergy":-5.096,"__typename":"HeroStatsHeroDryadType"},{"heroId2":52,"matchCount":1251,"winCount":532,"synergy":-5.1,"__typename":"HeroStatsHeroDryadType"},{"heroId2":109,"matchCount":170,"winCount":89,"synergy":-5.163,"__typename":"HeroStatsHeroDryadType"},{"heroId2":81,"matchCount":528,"winCount":266,"synergy":-5.615,"__typename":"HeroStatsHeroDryadType"}]